determinismus_kit/__init__.py
determinismus_kit/__main__.py
determinismus_kit/cli.py
determinismus_kit/core.py
determinismus_kit-0.1.1.dist-info/licenses/LICENSE
determinismus_kit-0.1.1.dist-info/METADATA
determinismus_kit-0.1.1.dist-info/WHEEL
determinismus_kit-0.1.1.dist-info/entry_points.txt
determinismus_kit-0.1.1.dist-info/top_level.txt
determinismus_kit-0.1.1.dist-info/RECORD
