Metadata-Version: 2.4
Name: determinismus-kit
Version: 0.1.1
Summary: Kleines Determinismus-Kit für reproduzierbare Python-Läufe (Seeds, Threads, Snapshots, optional PyTorch/NumPy).
Author: Dein Name
License-Expression: MIT
Requires-Python: >=3.8
License-File: LICENSE
Provides-Extra: torch
Requires-Dist: torch; extra == "torch"
Provides-Extra: numpy
Requires-Dist: numpy; extra == "numpy"
Dynamic: license-file
